MANIFEST.in
README.rst
setup.cfg
setup.py
axf/__init__.py
axf/axel.py
axf/bootstrap.py
axf/dateformat.py
axf/ractive.py
axf/validators.py
axf.egg-info/PKG-INFO
axf.egg-info/SOURCES.txt
axf.egg-info/dependency_links.txt
axf.egg-info/entry_points.txt
axf.egg-info/not-zip-safe
axf.egg-info/requires.txt
axf.egg-info/top_level.txt
axf/widgets/__init__.py
axf/widgets/ajax_autocomplete_field/__init__.py
axf/widgets/ajax_autocomplete_field/scripts.js
axf/widgets/ajax_autocomplete_field/widget.py
axf/widgets/ajax_autocomplete_field/resources/new_arrow.png
axf/widgets/ajax_autocomplete_field/resources/select2.css
axf/widgets/ajax_autocomplete_field/resources/select2.min.js
axf/widgets/ajax_autocomplete_field/resources/select2.png
axf/widgets/ajax_autocomplete_field/resources/select2x2.png
axf/widgets/ajax_autocomplete_field/resources/spinner.gif
axf/widgets/ajax_cascading_field/__init__.py
axf/widgets/ajax_cascading_field/scripts.js
axf/widgets/ajax_cascading_field/widget.py
axf/widgets/ajax_manage_photos/__init__.py
axf/widgets/ajax_manage_photos/widget.py
axf/widgets/ajax_manage_photos/resources/formdata.js
axf/widgets/ajax_multiple_cascading_single_select/__init__.py
axf/widgets/ajax_multiple_cascading_single_select/scripts.js
axf/widgets/ajax_multiple_cascading_single_select/widget.py
axf/widgets/ajax_single_select/__init__.py
axf/widgets/ajax_single_select/scripts.js
axf/widgets/ajax_single_select/widget.py
axf/widgets/bootstrap3/__init__.py
axf/widgets/bootstrap3/forms.py
axf/widgets/bootstrap3/templates/__init__.py
axf/widgets/bootstrap3/templates/horizontal_layout.html
axf/widgets/file_field/__init__.py
axf/widgets/file_field/widget.py
axf/widgets/file_field/templates/__init__.py
axf/widgets/file_field/templates/avatar_file_field.html
axf/widgets/monthly_date_field/__init__.py
axf/widgets/monthly_date_field/widget.py
axf/widgets/single_select_with_add/__init__.py
axf/widgets/single_select_with_add/scripts.js
axf/widgets/single_select_with_add/single_select_with_add.html
axf/widgets/single_select_with_add/widget.py
axf/widgets/wysihtml5_text_area/__init__.py
axf/widgets/wysihtml5_text_area/scripts.js
axf/widgets/wysihtml5_text_area/widget.py
