Metadata-Version: 1.0
Name: axf
Version: 0.0.19
Summary: AXANT ToscaWidget2 Widgets collection
Home-page: https://bitbucket.org/axant/axf
Author: Alessandro Molina
Author-email: alessandro.molina@axant.it
License: MIT
Platform: UNKNOWN
